{
  "version": "5",
  "dialect": "sqlite",
  "id": "e1b7a083-a5d6-4df0-b515-5dff4f048d48",
  "prevId": "00000000-0000-0000-0000-000000000000",
  "tables": {
    "dogs": {
      "name": "dogs",
      "columns": {
        "id": {
          "name": "id",
          "type": "integer",
          "primaryKey": true,
          "notNull": true,
          "autoincrement": false
        },
        "name": {
          "name": "name",
          "type": "text",
          "primaryKey": false,
          "notNull": true
        },
        "breed": {
          "name": "breed",
          "type": "text",
          "primaryKey": false,
          "notNull": true
        }
      },
      "indexes": {},
      "foreignKeys": {},
      "compositePrimaryKeys": {}
    }
  },
  "enums": {},
  "_meta": {
    "schemas": {},
    "tables": {},
    "columns": {}
  }
}